vogent_turn/__init__.py
vogent_turn/inference.py
vogent_turn/predict.py
vogent_turn/smollm_whisper.py
vogent_turn/whisper.py
vogent_turn-0.1.0.dist-info/METADATA
vogent_turn-0.1.0.dist-info/WHEEL
vogent_turn-0.1.0.dist-info/entry_points.txt
vogent_turn-0.1.0.dist-info/licenses/LICENSE
vogent_turn-0.1.0.dist-info/RECORD
