Metadata-Version: 2.4
Name: vogent-turn
Version: 0.1.0
Summary: Lightweight turn detection library for conversational AI
Project-URL: Homepage, https://github.com/vogent/vogent-turn
Project-URL: Repository, https://github.com/vogent/vogent-turn
Project-URL: Issues, https://github.com/vogent/vogent-turn/issues
Author: Vogent
License: Apache-2.0
License-File: LICENSE
Keywords: conversation-ai,multimodal,speech,turn-detection,voice,whisper
Classifier: Development Status :: 4 - Beta
Classifier: Intended Audience :: Developers
Classifier: License :: OSI Approved :: Apache Software License
Classifier: Programming Language :: Python :: 3
Classifier: Programming Language :: Python :: 3.8
Classifier: Programming Language :: Python :: 3.9
Classifier: Programming Language :: Python :: 3.10
Classifier: Programming Language :: Python :: 3.11
Classifier: Programming Language :: Python :: 3.12
Classifier: Topic :: Multimedia :: Sound/Audio :: Speech
Classifier: Topic :: Scientific/Engineering :: Artificial Intelligence
Requires-Python: >=3.10
Requires-Dist: cffi>=1.15.0
Requires-Dist: huggingface-hub>=0.19.0
Requires-Dist: librosa==0.10.1
Requires-Dist: numpy<2.0,>=1.26.0
Requires-Dist: onnx==1.18.0
Requires-Dist: onnxruntime-gpu==1.22.*; (platform_system == 'Linux' or platform_system == 'Windows') and platform_machine == 'x86_64'
Requires-Dist: onnxruntime>=1.22.1; (platform_system != 'Linux' and platform_system != 'Windows') or platform_machine != 'x86_64'
Requires-Dist: resampy>=0.4.2
Requires-Dist: soundfile>=0.12.0
Requires-Dist: torch==2.8.0
Requires-Dist: torchaudio==2.8.0
Requires-Dist: transformers==4.53.3
Provides-Extra: dev
Requires-Dist: build>=1.0.0; extra == 'dev'
Requires-Dist: pytest>=7.0.0; extra == 'dev'
Requires-Dist: ruff>=0.1.0; extra == 'dev'
Requires-Dist: twine>=4.0.0; extra == 'dev'
